{ "ente_codice": "048054_sn", "atto_data": "17/04/2018", "pubblicazione_numero": "2670", "atto_oggetto": "P.E.E.P. San Donato - bando per aree destinate a attrezzature pubbliche e commerciali  - In data 25 giugno 2012  è stato indetto un bando per l'assegnazione dell 'area destinata a attrezzature pubbliche e commerciali   compresa nel P.E.E.P. di San...", "atto_link": "http://www.tavarnellevp.it/servizi/scheda-servizio/peep-san-donato-bando-per-aree-destinate-a-attrezzature-pubbliche-e", "file_link": "http://www.tavarnellevp.it/servizi/scheda-servizio/peep-san-donato-bando-per-aree-destinate-a-attrezzature-pubbliche-e", "atto_tipo": "servizi web", "atto_numero": "2670", "ente_nome": "servizi web www.tavarnellevp.it", "pubblicazione_anno": "2018"}