{ "ente_codice": "048054_sn", "atto_data": "17/04/2018", "pubblicazione_numero": "2216", "atto_oggetto": "Trasporto per elettori disabili  - Il Comune di Tavarnelle Val di Pesa in collaborazione con la Misericordia di Tavarnelle V.P. e Barberino V.E. e l'Auser, organizza un servizio di trasporto rivolto alle persone disabili ed in...", "atto_link": "http://www.tavarnellevp.it/servizi/scheda-servizio/trasporto-per-elettori-disabili", "file_link": "http://www.tavarnellevp.it/servizi/scheda-servizio/trasporto-per-elettori-disabili", "atto_tipo": "servizi web", "atto_numero": "2216", "ente_nome": "servizi web www.tavarnellevp.it", "pubblicazione_anno": "2018"}