{
    "sentences": [
        {
            "index": 0, 
            "tokens": [
                {
                    "characterOffsetBegin": 0, 
                    "characterOffsetEnd": 6, 
                    "index": 1, 
                    "lemma": "asfalto", 
                    "originalText": "Asfalto", 
                    "pos": "S", 
                    "word": "Asfalto"
                }, 
                {
                    "characterOffsetBegin": 8, 
                    "characterOffsetEnd": 12, 
                    "index": 2, 
                    "lemma": "nuovo", 
                    "originalText": "nuovo", 
                    "pos": "A", 
                    "word": "nuovo"
                }, 
                {
                    "characterOffsetBegin": 14, 
                    "characterOffsetEnd": 15, 
                    "index": 3, 
                    "lemma": "in", 
                    "originalText": "in", 
                    "pos": "E", 
                    "word": "in"
                }, 
                {
                    "characterOffsetBegin": 17, 
                    "characterOffsetEnd": 25, 
                    "index": 4, 
                    "lemma": "v.Trieste", 
                    "originalText": "v.Trieste", 
                    "pos": "SP", 
                    "word": "v.Trieste"
                }, 
                {
                    "characterOffsetBegin": 26, 
                    "characterOffsetEnd": 26, 
                    "index": 5, 
                    "lemma": ",", 
                    "originalText": ",", 
                    "pos": "FF", 
                    "word": ","
                }, 
                {
                    "characterOffsetBegin": 28, 
                    "characterOffsetEnd": 37, 
                    "index": 6, 
                    "lemma": "v.Poccetti", 
                    "originalText": "v.Poccetti", 
                    "pos": "SP", 
                    "word": "v.Poccetti"
                }, 
                {
                    "characterOffsetBegin": 38, 
                    "characterOffsetEnd": 38, 
                    "index": 7, 
                    "lemma": ",", 
                    "originalText": ",", 
                    "pos": "FF", 
                    "word": ","
                }, 
                {
                    "characterOffsetBegin": 40, 
                    "characterOffsetEnd": 43, 
                    "index": 8, 
                    "lemma": "v.di", 
                    "originalText": "v.di", 
                    "pos": "NO", 
                    "word": "v.di"
                }, 
                {
                    "characterOffsetBegin": 45, 
                    "characterOffsetEnd": 50, 
                    "index": 9, 
                    "lemma": "Novoli", 
                    "originalText": "Novoli", 
                    "pos": "SP", 
                    "word": "Novoli"
                }, 
                {
                    "characterOffsetBegin": 51, 
                    "characterOffsetEnd": 51, 
                    "index": 10, 
                    "lemma": ",", 
                    "originalText": ",", 
                    "pos": "FF", 
                    "word": ","
                }, 
                {
                    "characterOffsetBegin": 53, 
                    "characterOffsetEnd": 59, 
                    "index": 11, 
                    "lemma": "v.Carlo", 
                    "originalText": "v.Carlo", 
                    "pos": "SP", 
                    "word": "v.Carlo"
                }, 
                {
                    "characterOffsetBegin": 61, 
                    "characterOffsetEnd": 63, 
                    "index": 12, 
                    "lemma": "di", 
                    "originalText": "del", 
                    "pos": "E", 
                    "word": "di"
                }, 
                {
                    "characterOffsetBegin": 61, 
                    "characterOffsetEnd": 63, 
                    "index": 13, 
                    "lemma": "il", 
                    "originalText": "del", 
                    "pos": "RD", 
                    "word": "il"
                }, 
                {
                    "characterOffsetBegin": 65, 
                    "characterOffsetEnd": 69, 
                    "index": 14, 
                    "lemma": "prete", 
                    "originalText": "Prete", 
                    "pos": "S", 
                    "word": "Prete"
                }, 
                {
                    "characterOffsetBegin": 70, 
                    "characterOffsetEnd": 70, 
                    "index": 15, 
                    "lemma": ",", 
                    "originalText": ",", 
                    "pos": "FF", 
                    "word": ","
                }, 
                {
                    "characterOffsetBegin": 72, 
                    "characterOffsetEnd": 78, 
                    "index": 16, 
                    "lemma": "interni", 
                    "originalText": "interni", 
                    "pos": "S", 
                    "word": "interni"
                }, 
                {
                    "characterOffsetBegin": 80, 
                    "characterOffsetEnd": 90, 
                    "index": 17, 
                    "lemma": "Argingrosso", 
                    "originalText": "Argingrosso", 
                    "pos": "SP", 
                    "word": "Argingrosso"
                }, 
                {
                    "characterOffsetBegin": 91, 
                    "characterOffsetEnd": 91, 
                    "index": 18, 
                    "lemma": ",", 
                    "originalText": ",", 
                    "pos": "FF", 
                    "word": ","
                }, 
                {
                    "characterOffsetBegin": 93, 
                    "characterOffsetEnd": 102, 
                    "index": 19, 
                    "lemma": "v.Pionieri", 
                    "originalText": "v.Pionieri", 
                    "pos": "SP", 
                    "word": "v.Pionieri"
                }, 
                {
                    "characterOffsetBegin": 104, 
                    "characterOffsetEnd": 115, 
                    "index": 20, 
                    "lemma": "dell\u2019Aviazi\u2026", 
                    "originalText": "dell\u2019Aviazi\u2026", 
                    "pos": "SP", 
                    "word": "dell\u2019Aviazi\u2026"
                }, 
                {
                    "characterOffsetBegin": 117, 
                    "characterOffsetEnd": 138, 
                    "index": 21, 
                    "lemma": "https://t.co/HCGDSErKK0", 
                    "originalText": "https://t.co/HCGDSErKK0", 
                    "pos": "SP", 
                    "word": "https://t.co/HCGDSErKK0"
                }
            ]
        }
    ]
}