{
    "sentences": [
        {
            "index": 0, 
            "tokens": [
                {
                    "characterOffsetBegin": 0, 
                    "characterOffsetEnd": 7, 
                    "index": 1, 
                    "lemma": "prevedere", 
                    "originalText": "Prevista", 
                    "pos": "V", 
                    "word": "Prevista"
                }, 
                {
                    "characterOffsetBegin": 9, 
                    "characterOffsetEnd": 11, 
                    "index": 2, 
                    "lemma": "da", 
                    "originalText": "dalle", 
                    "pos": "E", 
                    "word": "da"
                }, 
                {
                    "characterOffsetBegin": 11, 
                    "characterOffsetEnd": 13, 
                    "index": 3, 
                    "lemma": "le", 
                    "originalText": "dalle", 
                    "pos": "RD", 
                    "word": "le"
                }, 
                {
                    "characterOffsetBegin": 15, 
                    "characterOffsetEnd": 16, 
                    "index": 4, 
                    "lemma": "10", 
                    "originalText": "10", 
                    "pos": "N", 
                    "word": "10"
                }, 
                {
                    "characterOffsetBegin": 18, 
                    "characterOffsetEnd": 19, 
                    "index": 5, 
                    "lemma": "a", 
                    "originalText": "alla", 
                    "pos": "E", 
                    "word": "a"
                }, 
                {
                    "characterOffsetBegin": 19, 
                    "characterOffsetEnd": 21, 
                    "index": 6, 
                    "lemma": "il", 
                    "originalText": "alla", 
                    "pos": "RD", 
                    "word": "la"
                }, 
                {
                    "characterOffsetBegin": 23, 
                    "characterOffsetEnd": 32, 
                    "index": 7, 
                    "lemma": "mezzanotte", 
                    "originalText": "mezzanotte", 
                    "pos": "S", 
                    "word": "mezzanotte"
                }, 
                {
                    "characterOffsetBegin": 34, 
                    "characterOffsetEnd": 40, 
                    "index": 8, 
                    "lemma": "allerta", 
                    "originalText": "allerta", 
                    "pos": "A", 
                    "word": "allerta"
                }, 
                {
                    "characterOffsetBegin": 42, 
                    "characterOffsetEnd": 47, 
                    "index": 9, 
                    "lemma": "codice", 
                    "originalText": "codice", 
                    "pos": "S", 
                    "word": "codice"
                }, 
                {
                    "characterOffsetBegin": 49, 
                    "characterOffsetEnd": 54, 
                    "index": 10, 
                    "lemma": "giallo", 
                    "originalText": "giallo", 
                    "pos": "A", 
                    "word": "giallo"
                }, 
                {
                    "characterOffsetBegin": 56, 
                    "characterOffsetEnd": 58, 
                    "index": 11, 
                    "lemma": "per", 
                    "originalText": "per", 
                    "pos": "E", 
                    "word": "per"
                }, 
                {
                    "characterOffsetBegin": 60, 
                    "characterOffsetEnd": 68, 
                    "index": 12, 
                    "lemma": "temporale", 
                    "originalText": "temporali", 
                    "pos": "S", 
                    "word": "temporali"
                }, 
                {
                    "characterOffsetBegin": 70, 
                    "characterOffsetEnd": 74, 
                    "index": 13, 
                    "lemma": "forte", 
                    "originalText": "forti", 
                    "pos": "A", 
                    "word": "forti"
                }, 
                {
                    "characterOffsetBegin": 76, 
                    "characterOffsetEnd": 90, 
                    "index": 14, 
                    "lemma": "@ProtCivComuneFi", 
                    "originalText": "@ProtCivComuneFi", 
                    "pos": "SP", 
                    "word": "@ProtCivComuneFi"
                }
            ]
        }
    ]
}