{
    "sentences": [
        {
            "index": 0, 
            "tokens": [
                {
                    "characterOffsetBegin": 0, 
                    "characterOffsetEnd": 5, 
                    "index": 1, 
                    "lemma": "piazza", 
                    "originalText": "Piazza", 
                    "pos": "S", 
                    "word": "Piazza"
                }, 
                {
                    "characterOffsetBegin": 7, 
                    "characterOffsetEnd": 9, 
                    "index": 2, 
                    "lemma": "di", 
                    "originalText": "dei", 
                    "pos": "E", 
                    "word": "di"
                }, 
                {
                    "characterOffsetBegin": 8, 
                    "characterOffsetEnd": 9, 
                    "index": 3, 
                    "lemma": "i", 
                    "originalText": "dei", 
                    "pos": "RD", 
                    "word": "i"
                }, 
                {
                    "characterOffsetBegin": 11, 
                    "characterOffsetEnd": 16, 
                    "index": 4, 
                    "lemma": "ciompo", 
                    "originalText": "Ciompi", 
                    "pos": "SP", 
                    "word": "Ciompi"
                }, 
                {
                    "characterOffsetBegin": 18, 
                    "characterOffsetEnd": 18, 
                    "index": 5, 
                    "lemma": "a", 
                    "originalText": "a", 
                    "pos": "E", 
                    "word": "a"
                }, 
                {
                    "characterOffsetBegin": 20, 
                    "characterOffsetEnd": 26, 
                    "index": 6, 
                    "lemma": "Firenze", 
                    "originalText": "Firenze", 
                    "pos": "SP", 
                    "word": "Firenze"
                }, 
                {
                    "characterOffsetBegin": 28, 
                    "characterOffsetEnd": 29, 
                    "index": 7, 
                    "lemma": "si", 
                    "originalText": "si", 
                    "pos": "PC", 
                    "word": "si"
                }, 
                {
                    "characterOffsetBegin": 31, 
                    "characterOffsetEnd": 35, 
                    "index": 8, 
                    "lemma": "vestire", 
                    "originalText": "veste", 
                    "pos": "V", 
                    "word": "veste"
                }, 
                {
                    "characterOffsetBegin": 37, 
                    "characterOffsetEnd": 38, 
                    "index": 9, 
                    "lemma": "di", 
                    "originalText": "di", 
                    "pos": "E", 
                    "word": "di"
                }, 
                {
                    "characterOffsetBegin": 40, 
                    "characterOffsetEnd": 44, 
                    "index": 10, 
                    "lemma": "libri", 
                    "originalText": "libri", 
                    "pos": "S", 
                    "word": "libri"
                }, 
                {
                    "characterOffsetBegin": 46, 
                    "characterOffsetEnd": 46, 
                    "index": 11, 
                    "lemma": "e", 
                    "originalText": "e", 
                    "pos": "CC", 
                    "word": "e"
                }, 
                {
                    "characterOffsetBegin": 48, 
                    "characterOffsetEnd": 52, 
                    "index": 12, 
                    "lemma": "fiori", 
                    "originalText": "fiori", 
                    "pos": "S", 
                    "word": "fiori"
                }, 
                {
                    "characterOffsetBegin": 54, 
                    "characterOffsetEnd": 58, 
                    "index": 13, 
                    "lemma": "[news", 
                    "originalText": "[news", 
                    "pos": "A", 
                    "word": "[news"
                }, 
                {
                    "characterOffsetBegin": 60, 
                    "characterOffsetEnd": 69, 
                    "index": 14, 
                    "lemma": "aggiornare", 
                    "originalText": "aggiornata", 
                    "pos": "V", 
                    "word": "aggiornata"
                }, 
                {
                    "characterOffsetBegin": 71, 
                    "characterOffsetEnd": 72, 
                    "index": 15, 
                    "lemma": "a", 
                    "originalText": "alle", 
                    "pos": "E", 
                    "word": "a"
                }, 
                {
                    "characterOffsetBegin": 72, 
                    "characterOffsetEnd": 74, 
                    "index": 16, 
                    "lemma": "le", 
                    "originalText": "alle", 
                    "pos": "RD", 
                    "word": "le"
                }, 
                {
                    "characterOffsetBegin": 76, 
                    "characterOffsetEnd": 81, 
                    "index": 17, 
                    "lemma": "15:48]", 
                    "originalText": "15:48]", 
                    "pos": "N", 
                    "word": "15:48]"
                }, 
                {
                    "characterOffsetBegin": 83, 
                    "characterOffsetEnd": 104, 
                    "index": 18, 
                    "lemma": "https://t.co/8txvqRMY7K", 
                    "originalText": "https://t.co/8txvqRMY7K", 
                    "pos": "SP", 
                    "word": "https://t.co/8txvqRMY7K"
                }
            ]
        }
    ]
}