{
    "sentences": [
        {
            "index": 0, 
            "tokens": [
                {
                    "characterOffsetBegin": 0, 
                    "characterOffsetEnd": 4, 
                    "index": 1, 
                    "lemma": "Masks", 
                    "originalText": "Masks", 
                    "pos": "SP", 
                    "word": "Masks"
                }, 
                {
                    "characterOffsetBegin": 6, 
                    "characterOffsetEnd": 15, 
                    "index": 2, 
                    "lemma": "obligatory", 
                    "originalText": "obligatory", 
                    "pos": "S", 
                    "word": "obligatory"
                }, 
                {
                    "characterOffsetBegin": 17, 
                    "characterOffsetEnd": 19, 
                    "index": 3, 
                    "lemma": "for", 
                    "originalText": "for", 
                    "pos": "E", 
                    "word": "for"
                }, 
                {
                    "characterOffsetBegin": 21, 
                    "characterOffsetEnd": 26, 
                    "index": 4, 
                    "lemma": "anyone", 
                    "originalText": "anyone", 
                    "pos": "S", 
                    "word": "anyone"
                }, 
                {
                    "characterOffsetBegin": 28, 
                    "characterOffsetEnd": 34, 
                    "index": 5, 
                    "lemma": "outside", 
                    "originalText": "outside", 
                    "pos": "A", 
                    "word": "outside"
                }, 
                {
                    "characterOffsetBegin": 36, 
                    "characterOffsetEnd": 37, 
                    "index": 6, 
                    "lemma": "in", 
                    "originalText": "in", 
                    "pos": "E", 
                    "word": "in"
                }, 
                {
                    "characterOffsetBegin": 39, 
                    "characterOffsetEnd": 47, 
                    "index": 7, 
                    "lemma": "#Florence", 
                    "originalText": "#Florence", 
                    "pos": "SP", 
                    "word": "#Florence"
                }, 
                {
                    "characterOffsetBegin": 49, 
                    "characterOffsetEnd": 52, 
                    "index": 8, 
                    "lemma": "from", 
                    "originalText": "from", 
                    "pos": "X", 
                    "word": "from"
                }, 
                {
                    "characterOffsetBegin": 54, 
                    "characterOffsetEnd": 58, 
                    "index": 9, 
                    "lemma": "TODAY", 
                    "originalText": "TODAY", 
                    "pos": "SP", 
                    "word": "TODAY"
                }, 
                {
                    "characterOffsetBegin": 60, 
                    "characterOffsetEnd": 66, 
                    "index": 10, 
                    "lemma": "onwards", 
                    "originalText": "onwards", 
                    "pos": "S", 
                    "word": "onwards"
                }, 
                {
                    "characterOffsetBegin": 67, 
                    "characterOffsetEnd": 67, 
                    "index": 11, 
                    "lemma": ".", 
                    "originalText": ".", 
                    "pos": "FS", 
                    "word": "."
                }
            ]
        }, 
        {
            "index": 1, 
            "tokens": [
                {
                    "characterOffsetBegin": 69, 
                    "characterOffsetEnd": 71, 
                    "index": 1, 
                    "lemma": "FYI", 
                    "originalText": "FYI", 
                    "pos": "SP", 
                    "word": "FYI"
                }, 
                {
                    "characterOffsetBegin": 72, 
                    "characterOffsetEnd": 72, 
                    "index": 2, 
                    "lemma": ":", 
                    "originalText": ":", 
                    "pos": "FC", 
                    "word": ":"
                }, 
                {
                    "characterOffsetBegin": 74, 
                    "characterOffsetEnd": 79, 
                    "index": 3, 
                    "lemma": "Please", 
                    "originalText": "Please", 
                    "pos": "SP", 
                    "word": "Please"
                }, 
                {
                    "characterOffsetBegin": 81, 
                    "characterOffsetEnd": 84, 
                    "index": 4, 
                    "lemma": "don'", 
                    "originalText": "don'", 
                    "pos": "E", 
                    "word": "don'"
                }, 
                {
                    "characterOffsetBegin": 85, 
                    "characterOffsetEnd": 85, 
                    "index": 5, 
                    "lemma": "t", 
                    "originalText": "t", 
                    "pos": "X", 
                    "word": "t"
                }, 
                {
                    "characterOffsetBegin": 87, 
                    "characterOffsetEnd": 92, 
                    "index": 6, 
                    "lemma": "litter", 
                    "originalText": "litter", 
                    "pos": "S", 
                    "word": "litter"
                }, 
                {
                    "characterOffsetBegin": 94, 
                    "characterOffsetEnd": 96, 
                    "index": 7, 
                    "lemma": "and", 
                    "originalText": "and", 
                    "pos": "CC", 
                    "word": "and"
                }, 
                {
                    "characterOffsetBegin": 98, 
                    "characterOffsetEnd": 102, 
                    "index": 8, 
                    "lemma": "leave", 
                    "originalText": "leave", 
                    "pos": "S", 
                    "word": "leave"
                }, 
                {
                    "characterOffsetBegin": 104, 
                    "characterOffsetEnd": 107, 
                    "index": 9, 
                    "lemma": "your", 
                    "originalText": "your", 
                    "pos": "E", 
                    "word": "your"
                }, 
                {
                    "characterOffsetBegin": 109, 
                    "characterOffsetEnd": 114, 
                    "index": 10, 
                    "lemma": "masks/", 
                    "originalText": "masks/", 
                    "pos": "S", 
                    "word": "masks/"
                }, 
                {
                    "characterOffsetBegin": 115, 
                    "characterOffsetEnd": 120, 
                    "index": 11, 
                    "lemma": "gloves", 
                    "originalText": "gloves", 
                    "pos": "S", 
                    "word": "gloves"
                }, 
                {
                    "characterOffsetBegin": 122, 
                    "characterOffsetEnd": 123, 
                    "index": 12, 
                    "lemma": "on", 
                    "originalText": "on", 
                    "pos": "FF", 
                    "word": "on"
                }, 
                {
                    "characterOffsetBegin": 125, 
                    "characterOffsetEnd": 127, 
                    "index": 13, 
                    "lemma": "the", 
                    "originalText": "the", 
                    "pos": "RD", 
                    "word": "the"
                }, 
                {
                    "characterOffsetBegin": 129, 
                    "characterOffsetEnd": 134, 
                    "index": 14, 
                    "lemma": "ground", 
                    "originalText": "ground", 
                    "pos": "S", 
                    "word": "ground"
                }, 
                {
                    "characterOffsetBegin": 135, 
                    "characterOffsetEnd": 135, 
                    "index": 15, 
                    "lemma": ".", 
                    "originalText": ".", 
                    "pos": "FS", 
                    "word": "."
                }
            ]
        }, 
        {
            "index": 2, 
            "tokens": [
                {
                    "characterOffsetBegin": 137, 
                    "characterOffsetEnd": 141, 
                    "index": 1, 
                    "lemma": "There", 
                    "originalText": "There", 
                    "pos": "SP", 
                    "word": "There"
                }, 
                {
                    "characterOffsetBegin": 143, 
                    "characterOffsetEnd": 145, 
                    "index": 2, 
                    "lemma": "are", 
                    "originalText": "are", 
                    "pos": "V", 
                    "word": "are"
                }, 
                {
                    "characterOffsetBegin": 147, 
                    "characterOffsetEnd": 152, 
                    "index": 3, 
                    "lemma": "plenty", 
                    "originalText": "plenty", 
                    "pos": "S", 
                    "word": "plenty"
                }, 
                {
                    "characterOffsetBegin": 154, 
                    "characterOffsetEnd": 155, 
                    "index": 4, 
                    "lemma": "of", 
                    "originalText": "of", 
                    "pos": "E", 
                    "word": "of"
                }, 
                {
                    "characterOffsetBegin": 157, 
                    "characterOffsetEnd": 161, 
                    "index": 5, 
                    "lemma": "trash", 
                    "originalText": "trash", 
                    "pos": "A", 
                    "word": "trash"
                }, 
                {
                    "characterOffsetBegin": 163, 
                    "characterOffsetEnd": 166, 
                    "index": 6, 
                    "lemma": "bins", 
                    "originalText": "bins", 
                    "pos": "S", 
                    "word": "bins"
                }, 
                {
                    "characterOffsetBegin": 168, 
                    "characterOffsetEnd": 173, 
                    "index": 7, 
                    "lemma": "around", 
                    "originalText": "around", 
                    "pos": "A", 
                    "word": "around"
                }, 
                {
                    "characterOffsetBegin": 175, 
                    "characterOffsetEnd": 178, 
                    "index": 8, 
                    "lemma": "town", 
                    "originalText": "town", 
                    "pos": "X", 
                    "word": "town"
                }, 
                {
                    "characterOffsetBegin": 179, 
                    "characterOffsetEnd": 179, 
                    "index": 9, 
                    "lemma": ".", 
                    "originalText": ".", 
                    "pos": "FS", 
                    "word": "."
                }
            ]
        }, 
        {
            "index": 3, 
            "tokens": [
                {
                    "characterOffsetBegin": 181, 
                    "characterOffsetEnd": 194, 
                    "index": 1, 
                    "lemma": "@DarioNardella", 
                    "originalText": "@DarioNardella", 
                    "pos": "V", 
                    "word": "@DarioNardella"
                }, 
                {
                    "characterOffsetBegin": 196, 
                    "characterOffsetEnd": 204, 
                    "index": 2, 
                    "lemma": "@comunefi", 
                    "originalText": "@comunefi", 
                    "pos": "A", 
                    "word": "@comunefi"
                }, 
                {
                    "characterOffsetBegin": 206, 
                    "characterOffsetEnd": 227, 
                    "index": 3, 
                    "lemma": "https://t.co/2QU1hrouIZ", 
                    "originalText": "https://t.co/2QU1hrouIZ", 
                    "pos": "SP", 
                    "word": "https://t.co/2QU1hrouIZ"
                }
            ]
        }
    ]
}